odoo/addons/mail_browser_view/README.rst
odoo/addons/mail_browser_view/__init__.py
odoo/addons/mail_browser_view/__manifest__.py
odoo/addons/mail_browser_view/controllers/__init__.py
odoo/addons/mail_browser_view/controllers/browser_view.py
odoo/addons/mail_browser_view/data/ir_config.xml
odoo/addons/mail_browser_view/demo/mail.xml
odoo/addons/mail_browser_view/i18n/mail_browser_view.pot
odoo/addons/mail_browser_view/models/__init__.py
odoo/addons/mail_browser_view/models/mail_mail.py
odoo/addons/mail_browser_view/readme/CONFIGURE.rst
odoo/addons/mail_browser_view/readme/CONTRIBUTORS.rst
odoo/addons/mail_browser_view/readme/DESCRIPTION.rst
odoo/addons/mail_browser_view/readme/USAGE.rst
odoo/addons/mail_browser_view/static/description/icon.png
odoo/addons/mail_browser_view/static/description/index.html
odoo/addons/mail_browser_view/tests/__init__.py
odoo/addons/mail_browser_view/tests/test_mail_browser_view.py
odoo11_addon_mail_browser_view-11.0.1.0.0.99.dev3.dist-info/METADATA
odoo11_addon_mail_browser_view-11.0.1.0.0.99.dev3.dist-info/WHEEL
odoo11_addon_mail_browser_view-11.0.1.0.0.99.dev3.dist-info/top_level.txt
odoo11_addon_mail_browser_view-11.0.1.0.0.99.dev3.dist-info/RECORD
